pybind11_coordtransform/__init__.py
pybind11_coordtransform/__main__.py
pybind11_coordtransform/_core.cp310-win_amd64.pyd
pybind11_coordtransform/_core.pyi
pybind11_coordtransform/py.typed
pybind11_coordtransform-0.1.2.dist-info/METADATA
pybind11_coordtransform-0.1.2.dist-info/WHEEL
pybind11_coordtransform-0.1.2.dist-info/licenses/LICENSE
pybind11_coordtransform-0.1.2.dist-info/RECORD
