Metadata-Version: 2.1
Name: pybind11_coordtransform
Version: 0.1.2
Summary: c++/python version of coordtransform
Author-Email: district10 <dvorak4tzx@gmail.com>
Classifier: Development Status :: 4 - Beta
Classifier: License :: OSI Approved :: MIT License
Classifier: Programming Language :: Python :: 3 :: Only
Classifier: Programming Language :: Python :: 3.7
Classifier: Programming Language :: Python :: 3.8
Classifier: Programming Language :: Python :: 3.9
Classifier: Programming Language :: Python :: 3.10
Classifier: Programming Language :: Python :: 3.11
Project-URL: Homepage, https://github.com/cubao/pybind11_coordtransform
Requires-Python: >=3.7
Provides-Extra: test
Requires-Dist: pytest; extra == "test"
